{
 "absolute_value": 0,
 "align_labels_right": 0,
 "creation": "2025-11-12 09:44:01.760995",
 "custom_format": 1,
 "default_print_language": "en",
 "disabled": 0,
 "doc_type": "Room",
 "docstatus": 0,
 "doctype": "Print Format",
 "font_size": 14,
 "html": "<div style=\"text-align: center; border: 1px solid #000; padding: 20px; width: 350px; margin: auto; font-family: Arial, sans-serif;\">\r\n    <!-- Room Info -->\r\n    <h3>ROOM {{ doc.room_number }}</h3>\r\n    <p style=\"margin: 10px 0;\">Scan QR Code to<br>Order a Service</p>\r\n    \r\n    <!-- QR Code - Dynamically Generated -->\r\n    {% set qr_base64 = frappe.call(\"igusto.igusto.doctype.room.room.generate_room_qr\", room_name=doc.name) %}\r\n    <div style=\"margin: 15px 0;\">\r\n        {% if qr_base64 %}\r\n            <img src=\"data:image/png;base64,{{ qr_base64 }}\" \r\n                 width=\"200\" height=\"200\" \r\n                 style=\"display: block; margin: 0 auto;\">\r\n        {% else %}\r\n            <p style=\"color: #999;\">QR Code not available</p>\r\n        {% endif %}\r\n    </div>\r\n    \r\n    <!-- Company Info -->\r\n    {% set company_name = frappe.db.get_single_value(\"Global Defaults\", \"default_company\") %}\r\n    {% if company_name %}\r\n        {% set company = frappe.get_doc(\"Company\", company_name) %}\r\n        \r\n        <!-- Company Logo from Attachments -->\r\n        {% set logo_file = frappe.db.sql(\"\"\"\r\n            SELECT file_url \r\n            FROM `tabFile` \r\n            WHERE attached_to_doctype = 'Company' \r\n            AND attached_to_name = %s \r\n            AND is_private = 0\r\n            LIMIT 1\r\n        \"\"\", (company.name,), as_dict=1) %}\r\n        \r\n        {% if logo_file and logo_file[0] and logo_file[0].file_url %}\r\n            <div style=\"margin: 15px 0;\">\r\n                <img src=\"{{ logo_file[0].file_url }}\" alt=\"Company Logo\" width=\"90\" height=\"90\" style=\"object-fit: contain; border-radius: 50%;\">\r\n            </div>\r\n        {% else %}\r\n            <p style=\"font-size: 12px; color: #888;\">(No company logo)</p>\r\n        {% endif %}\r\n        \r\n        <h4 style=\"margin: 5px 0;\">{{ company.company_name }}</h4>\r\n        \r\n        <!-- Company Address (is_your_company_address = Yes) -->\r\n        {% set address_link = frappe.db.get_value(\"Dynamic Link\", \r\n            {\r\n                \"link_doctype\": \"Company\",\r\n                \"link_name\": company.name,\r\n                \"parenttype\": \"Address\"\r\n            }, \r\n            \"parent\") %}\r\n        \r\n        {% if address_link %}\r\n            {% set company_address = frappe.get_doc(\"Address\", address_link) %}\r\n            {% if company_address.is_your_company_address == 1 %}\r\n                <div style=\"font-size: 12px; margin: 5px 0;\">\r\n                    {% if company_address.address_line1 %}{{ company_address.address_line1 }}<br>{% endif %}\r\n                    {% if company_address.address_line2 %}{{ company_address.address_line2 }}<br>{% endif %}\r\n                    {% if company_address.city %}{{ company_address.city }}{% endif %}\r\n                    {% if company_address.state %}, {{ company_address.state }}{% endif %}\r\n                    {% if company_address.pincode %} - {{ company_address.pincode }}{% endif %}\r\n                    {% if company_address.country %}<br>{{ company_address.country }}{% endif %}\r\n                </div>\r\n            {% endif %}\r\n        {% endif %}\r\n        \r\n        <!-- Contact Info -->\r\n        <div style=\"font-size: 12px; margin-top: 10px;\">\r\n            {% if company.phone_no %}\ud83d\udcde {{ company.phone_no }}{% endif %}\r\n            <br>\r\n            {% if company.email %}\u2709\ufe0f {{ company.email }}{% endif %}\r\n        </div>\r\n    {% endif %}\r\n</div>",
 "idx": 0,
 "line_breaks": 0,
 "margin_bottom": 15.0,
 "margin_left": 15.0,
 "margin_right": 15.0,
 "margin_top": 15.0,
 "modified": "2025-11-14 17:05:00.939694",
 "modified_by": "Administrator",
 "module": "igusto",
 "name": "Room Order",
 "owner": "Administrator",
 "page_number": "Hide",
 "pdf_generator": "wkhtmltopdf",
 "print_format_builder": 0,
 "print_format_builder_beta": 0,
 "print_format_type": "Jinja",
 "raw_printing": 0,
 "show_section_headings": 0,
 "standard": "Yes"
}